darshan.libs/libdarshan-util-18cc005b.so.0.0.0
darshan-3.5.0.dist-info/WHEEL
darshan-3.5.0.dist-info/RECORD
darshan-3.5.0.dist-info/top_level.txt
darshan-3.5.0.dist-info/METADATA
darshan/extension.cpython-311-x86_64-linux-gnu.so
darshan/report.py
darshan/discover_darshan.py
darshan/__init__.py
darshan/log_utils.py
darshan/__main__.py
darshan/extension.c
darshan/tests/test_plot_io_cost.py
darshan/tests/test_lib_accum.py
darshan/tests/test_data_access_by_filesystem.py
darshan/tests/test_report.py
darshan/tests/__init__.py
darshan/tests/conftest.py
darshan/tests/test_plot_dxt_heatmap.py
darshan/tests/test_modposix.py
darshan/tests/test_plot_exp_common.py
darshan/tests/test_moddxt.py
darshan/tests/test_plot_common_access_table.py
darshan/tests/test_log_utils.py
darshan/tests/test_job_stats.py
darshan/tests/test_summary.py
darshan/tests/test_file_stats.py
darshan/tests/test_heatmap_handling.py
darshan/tests/test_error.py
darshan/tests/test_modmpiio.py
darshan/tests/test_modstdio.py
darshan/tests/test_cffi_misc.py
darshan/tests/test_report_copy.py
darshan/tests/input/noposix.darshan
darshan/tests/input/__init__.py
darshan/tests/input/sample.darshan
darshan/tests/input/match_jsonout.json
darshan/tests/input/sample-dxt-simple.darshan
darshan/tests/input/match_dotout.dot
darshan/tests/input/sample-goodost.darshan
darshan/tests/input/noposixopens.darshan
darshan/tests/input/sample-badost.darshan
darshan/backend/apxc.py
darshan/backend/__init__.py
darshan/backend/cffi_backend.py
darshan/backend/apss.py
darshan/backend/api_def_c.py
darshan/backend/apmpi.py
darshan/experimental/__init__.py
darshan/experimental/aggregators/create_time_summary.py
darshan/experimental/aggregators/__init__.py
darshan/experimental/aggregators/create_sankey.py
darshan/experimental/aggregators/summarize.py
darshan/experimental/aggregators/agg_ioops.py
darshan/experimental/aggregators/mod_agg_iohist.py
darshan/experimental/aggregators/create_timeline.py
darshan/experimental/aggregators/create_dxttimeline.py
darshan/experimental/aggregators/records_as_dict.py
