Metadata-Version: 2.4
Name: darshan
Version: 3.5.0
Summary: Python tools to interact with Darshan log records of HPC applications.
Project-URL: homepage, https://www.mcs.anl.gov/research/projects/darshan/
Project-URL: repository, https://github.com/darshan-hpc/darshan
Classifier: Development Status :: 4 - Beta
Classifier: Intended Audience :: Developers
Classifier: Intended Audience :: Science/Research
Classifier: Natural Language :: English
Classifier: Programming Language :: Python :: 3
Classifier: Programming Language :: Python :: 3.7
Classifier: Programming Language :: Python :: 3.8
Classifier: Programming Language :: Python :: 3.9
Classifier: Programming Language :: Python :: 3.10
Classifier: Programming Language :: Python :: 3.11
Classifier: Programming Language :: Python :: 3.12
Requires-Python: >=3.7
Requires-Dist: cffi
Requires-Dist: numpy
Requires-Dist: pandas
Requires-Dist: matplotlib
Requires-Dist: seaborn
Requires-Dist: mako
Requires-Dist: humanize
Requires-Dist: rich
Provides-Extra: test
Requires-Dist: packaging; extra == "test"
Requires-Dist: pytest; extra == "test"
Requires-Dist: lxml; extra == "test"
Requires-Dist: importlib_resources; python_version < "3.9" and extra == "test"
Provides-Extra: dev
Requires-Dist: sphinx; extra == "dev"
Requires-Dist: sphinx_rtd_theme; extra == "dev"
Requires-Dist: pipx; extra == "dev"
